lab6/lfsr/vsrc/top.v

//btn[0]代表时钟，为了方便nvboard，不过这里没用
//ledr[7:0]表征寄存器的值，seg[0]代表输出
//rst复位

module top(
    input clk,
    input rst,
    input [4:0] btn,
    input [15:0] sw,
    input ps2_clk,
    input ps2_data,
    output [15:0] ledr,
    output VGA_CLK,
    output VGA_HSYNC,
    output VGA_VSYNC,
    output VGA_BLANK_N,
    output [7:0] VGA_R,
    output [7:0] VGA_G,
    output [7:0] VGA_B,
    output [7:0] seg0,
    output [7:0] seg1,
    output [7:0] seg2,
    output [7:0] seg3,
    output [7:0] seg4,
    output [7:0] seg5,
    output [7:0] seg6,
    output [7:0] seg7
);

reg [7:0] shift_reg;
reg out;

assign seg0[0] = out;
assign ledr[7:0] = shift_reg;

always @(posedge btn or posedge rst) begin
    if (rst) begin
         shift_reg <= 8'b00000001;
    end 
    else begin
        shift_reg <= { shift_reg[4] ^ shift_reg[3] ^ shift_reg[2] ^ shift_reg[0], shift_reg[7:1]};
	out <= shift_reg[0];
    end
end



endmodule

lab6/lfsr/wave.vcd
$version Generated by VerilatedVcd $end
$timescale 1ps $end
 $scope module TOP $end
  $var wire 1 # clk $end
  $var wire 1 $ rst $end
  $var wire 5 % btn [4:0] $end
  $var wire 16 & sw [15:0] $end
  $var wire 1 ' ps2_clk $end
  $var wire 1 ( ps2_data $end
  $var wire 16 ) ledr [15:0] $end
  $var wire 1 * VGA_CLK $end
  $var wire 1 + VGA_HSYNC $end
  $var wire 1 , VGA_VSYNC $end
  $var wire 1 - VGA_BLANK_N $end
  $var wire 8 . VGA_R [7:0] $end
  $var wire 8 / VGA_G [7:0] $end
  $var wire 8 0 VGA_B [7:0] $end
  $var wire 8 1 seg0 [7:0] $end
  $var wire 8 2 seg1 [7:0] $end
  $var wire 8 3 seg2 [7:0] $end
  $var wire 8 4 seg3 [7:0] $end
  $var wire 8 5 seg4 [7:0] $end
  $var wire 8 6 seg5 [7:0] $end
  $var wire 8 7 seg6 [7:0] $end
  $var wire 8 8 seg7 [7:0] $end
  $scope module top $end
   $var wire 1 # clk $end
   $var wire 1 $ rst $end
   $var wire 5 % btn [4:0] $end
   $var wire 16 & sw [15:0] $end
   $var wire 1 ' ps2_clk $end
   $var wire 1 ( ps2_data $end
   $var wire 16 ) ledr [15:0] $end
   $var wire 1 * VGA_CLK $end
   $var wire 1 + VGA_HSYNC $end
   $var wire 1 , VGA_VSYNC $end
   $var wire 1 - VGA_BLANK_N $end
   $var wire 8 . VGA_R [7:0] $end
   $var wire 8 / VGA_G [7:0] $end
   $var wire 8 0 VGA_B [7:0] $end
   $var wire 8 1 seg0 [7:0] $end
   $var wire 8 2 seg1 [7:0] $end
   $var wire 8 3 seg2 [7:0] $end
   $var wire 8 4 seg3 [7:0] $end
   $var wire 8 5 seg4 [7:0] $end
   $var wire 8 6 seg5 [7:0] $end
   $var wire 8 7 seg6 [7:0] $end
   $var wire 8 8 seg7 [7:0] $end
   $var wire 8 9 shift_reg [7:0] $end
   $var wire 1 : out $end
  $upscope $end
 $upscope $end
$enddefinitions $end


#5
0#
0$
b00000 %
b0000000000000000 &
0'
0(
b0000000000000000 )
0*
0+
0,
0-
b00000000 .
b00000000 /
b00000000 0
b00000000 1
b00000000 2
b00000000 3
b00000000 4
b00000000 5
b00000000 6
b00000000 7
b00000000 8
b00000000 9
0:
#10
1$
b0000000000000001 )
b00000001 9
#15
0$
#16
#17
b00001 %
b0000000010000000 )
b00000001 1
b10000000 9
1:
#18
b00000 %
#19
b00001 %
b0000000001000000 )
b00000000 1
b01000000 9
0:
#20
b00000 %
#21
b00001 %
b0000000000100000 )
b00100000 9
#22
b00000 %
#23
b00001 %
b0000000000010000 )
b00010000 9
#24
b00000 %
#25
b00001 %
b0000000010001000 )
b10001000 9
#26
b00000 %
#27
b00001 %
b0000000011000100 )
b11000100 9
#28
b00000 %
#29
b00001 %
b0000000011100010 )
b11100010 9
#30
b00000 %
#31
b00001 %
b0000000001110001 )
b01110001 9
#32
b00000 %
#33
b00001 %
b0000000000111000 )
b00000001 1
b00111000 9
1:
#34
b00000 %
#35
b00001 %
b0000000000011100 )
b00000000 1
b00011100 9
0:
#36
b00000 %
#37
b00001 %
b0000000010001110 )
b10001110 9
#38
b00000 %
#39
b00001 %
b0000000001000111 )
b01000111 9
#40
b00000 %
#41
b00001 %
b0000000000100011 )
b00000001 1
b00100011 9
1:
#42
b00000 %
#43
b00001 %
b0000000010010001 )
b10010001 9
#44
b00000 %
#45
b00001 %
b0000000001001000 )
b01001000 9
#46
b00000 %
#47
b00001 %
b0000000010100100 )
b00000000 1
b10100100 9
0:
#48
b00000 %
#49
b00001 %
b0000000011010010 )
b11010010 9
#50
b00000 %
#51
b00001 %
b0000000011101001 )
b11101001 9
#52
b00000 %
#53
b00001 %
b0000000001110100 )
b00000001 1
b01110100 9
1:
#54
b00000 %
#55
b00001 %
b0000000000111010 )
b00000000 1
b00111010 9
0:
#56
b00000 %
#57
b00001 %
b0000000000011101 )
b00011101 9
#58
b00000 %
#59
b00001 %
b0000000000001110 )
b00000001 1
b00001110 9
1:
#60
b00000 %
#61
b00001 %
b0000000000000111 )
b00000000 1
b00000111 9
0:
#62
b00000 %
#63
b00001 %
b0000000000000011 )
b00000001 1
b00000011 9
1:
#64
b00000 %
#65
b00001 %
b0000000010000001 )
b10000001 9
#66
b00000 %
#67
b00001 %
b0000000011000000 )
b11000000 9
#68
b00000 %
#69
b00001 %
b0000000001100000 )
b00000000 1
b01100000 9
0:
#70
b00000 %
#71
b00001 %
b0000000000110000 )
b00110000 9
#72
b00000 %
#73
b00001 %
b0000000010011000 )
b10011000 9
#74
b00000 %
#75
b00001 %
b0000000001001100 )
b01001100 9
#76
b00000 %
#77
b00001 %
b0000000000100110 )
b00100110 9
#78
b00000 %
#79
b00001 %
b0000000010010011 )
b10010011 9
#80
b00000 %
#81
b00001 %
b0000000001001001 )
b00000001 1
b01001001 9
1:
#82
b00000 %
#83
b00001 %
b0000000000100100 )
b00100100 9
#84
b00000 %
#85
b00001 %
b0000000010010010 )
b00000000 1
b10010010 9
0:
#86
b00000 %
#87
b00001 %
b0000000011001001 )
b11001001 9
#88
b00000 %
#89
b00001 %
b0000000001100100 )
b00000001 1
b01100100 9
1:
#90
b00000 %
#91
b00001 %
b0000000010110010 )
b00000000 1
b10110010 9
0:
#92
b00000 %
#93
b00001 %
b0000000011011001 )
b11011001 9
#94
b00000 %
#95
b00001 %
b0000000011101100 )
b00000001 1
b11101100 9
1:
#96
b00000 %
#97
b00001 %
b0000000001110110 )
b00000000 1
b01110110 9
0:
#98
b00000 %
#99
b00001 %
b0000000000111011 )
b00111011 9
#100
b00000 %
#101
b00001 %
b0000000010011101 )
b00000001 1
b10011101 9
1:
#102
b00000 %
#103
b00001 %
b0000000001001110 )
b01001110 9
#104
b00000 %
#105
b00001 %
b0000000000100111 )
b00000000 1
b00100111 9
0:
#106
b00000 %
#107
b00001 %
b0000000000010011 )
b00000001 1
b00010011 9
1:
#108
b00000 %
#109
b00001 %
b0000000000001001 )
b00001001 9
#110
b00000 %
#111
b00001 %
b0000000000000100 )
b00000100 9
#112
b00000 %
#113
b00001 %
b0000000010000010 )
b00000000 1
b10000010 9
0:
#114
b00000 %
#115
b00001 %
b0000000001000001 )
b01000001 9
#116
b00000 %
#117
b00001 %
b0000000010100000 )
b00000001 1
b10100000 9
1:
#118
b00000 %
#119
b00001 %
b0000000001010000 )
b00000000 1
b01010000 9
0:
#120
b00000 %
#121
b00001 %
b0000000010101000 )
b10101000 9
#122
b00000 %
#123
b00001 %
b0000000011010100 )
b11010100 9
#124
b00000 %
#125
b00001 %
b0000000001101010 )
b01101010 9
#126
b00000 %
#127
b00001 %
b0000000010110101 )
b10110101 9
#128
b00000 %
#129
b00001 %
b0000000011011010 )
b00000001 1
b11011010 9
1:
#130
b00000 %
#131
b00001 %
b0000000001101101 )
b00000000 1
b01101101 9
0:
#132
b00000 %
#133
b00001 %
b0000000010110110 )
b00000001 1
b10110110 9
1:
#134
b00000 %
#135
b00001 %
b0000000001011011 )
b00000000 1
b01011011 9
0:
#136
b00000 %
#137
b00001 %
b0000000010101101 )
b00000001 1
b10101101 9
1:
#138
b00000 %
#139
b00001 %
b0000000011010110 )
b11010110 9
#140
b00000 %
#141
b00001 %
b0000000001101011 )
b00000000 1
b01101011 9
0:
#142
b00000 %
#143
b00001 %
b0000000000110101 )
b00000001 1
b00110101 9
1:
#144
b00000 %
#145
b00001 %
b0000000010011010 )
b10011010 9
#146
b00000 %
#147
b00001 %
b0000000001001101 )
b00000000 1
b01001101 9
0:
#148
b00000 %
#149
b00001 %
b0000000010100110 )
b00000001 1
b10100110 9
1:
#150
b00000 %
#151
b00001 %
b0000000011010011 )
b00000000 1
b11010011 9
0:
#152
b00000 %
#153
b00001 %
b0000000001101001 )
b00000001 1
b01101001 9
1:
#154
b00000 %
#155
b00001 %
b0000000000110100 )
b00110100 9
#156
b00000 %
#157
b00001 %
b0000000000011010 )
b00000000 1
b00011010 9
0:
#158
b00000 %
#159
b00001 %
b0000000000001101 )
b00001101 9
#160
b00000 %
#161
b00001 %
b0000000010000110 )
b00000001 1
b10000110 9
1:
#162
b00000 %
#163
b00001 %
b0000000011000011 )
b00000000 1
b11000011 9
0:
#164
b00000 %
#165
b00001 %
b0000000011100001 )
b00000001 1
b11100001 9
1:
#166
b00000 %
#167
b00001 %
b0000000011110000 )
b11110000 9
#168
b00000 %
#169
b00001 %
b0000000011111000 )
b00000000 1
b11111000 9
0:
#170
b00000 %
#171
b00001 %
b0000000001111100 )
b01111100 9
#172
b00000 %
#173
b00001 %
b0000000010111110 )
b10111110 9
#174
b00000 %
#175
b00001 %
b0000000011011111 )
b11011111 9
#176
b00000 %
#177
b00001 %
b0000000001101111 )
b00000001 1
b01101111 9
1:
#178
b00000 %
#179
b00001 %
b0000000010110111 )
b10110111 9
#180
b00000 %
#181
b00001 %
b0000000011011011 )
b11011011 9
#182
b00000 %
#183
b00001 %
b0000000011101101 )
b11101101 9
#184
b00000 %
#185
b00001 %
b0000000011110110 )
b11110110 9
#186
b00000 %
#187
b00001 %
b0000000001111011 )
b00000000 1
b01111011 9
0:
#188
b00000 %
#189
b00001 %
b0000000010111101 )
b00000001 1
b10111101 9
1:
#190
b00000 %
#191
b00001 %
b0000000001011110 )
b01011110 9
#192
b00000 %
#193
b00001 %
b0000000010101111 )
b00000000 1
b10101111 9
0:
#194
b00000 %
#195
b00001 %
b0000000011010111 )
b00000001 1
b11010111 9
1:
#196
b00000 %
#197
b00001 %
b0000000011101011 )
b11101011 9
#198
b00000 %
#199
b00001 %
b0000000001110101 )
b01110101 9
#200
b00000 %
#201
b00001 %
b0000000010111010 )
b10111010 9
#202
b00000 %
#203
b00001 %
b0000000001011101 )
b00000000 1
b01011101 9
0:
#204
b00000 %
#205
b00001 %
b0000000000101110 )
b00000001 1
b00101110 9
1:
#206
b00000 %
#207
b00001 %
b0000000000010111 )
b00000000 1
b00010111 9
0:
#208
b00000 %
#209
b00001 %
b0000000010001011 )
b00000001 1
b10001011 9
1:
#210
b00000 %
#211
b00001 %
b0000000001000101 )
b01000101 9
#212
b00000 %
#213
b00001 %
b0000000000100010 )
b00100010 9
#214
b00000 %
#215
b00001 %
b0000000000010001 )
b00000000 1
b00010001 9
0:
