lab6/shift_reg/vsrc/top.v


//ledr[7:0]代表各个位
//btn[0]给时钟，方便nvboard手动调时钟
//sw[0]给输入
//sw[15]控制左移和右移，1:左移，0:右移


module top(
    input clk,
    input rst,
    input [4:0] btn,
    input [15:0] sw,
    input ps2_clk,
    input ps2_data,
    output [15:0] ledr,
    output VGA_CLK,
    output VGA_HSYNC,
    output VGA_VSYNC,
    output VGA_BLANK_N,
    output [7:0] VGA_R,
    output [7:0] VGA_G,
    output [7:0] VGA_B,
    output [7:0] seg0,
    output [7:0] seg1,
    output [7:0] seg2,
    output [7:0] seg3,
    output [7:0] seg4,
    output [7:0] seg5,
    output [7:0] seg6,
    output [7:0] seg7
);



reg [7:0]q;


assign ledr[7:0] = q;

always@(posedge btn[0] or posedge rst) begin
    if(rst == 1'b1) begin
        q <= 8'b0;
    end
    else begin
        if(sw[15]==1'b0) begin
            q <= {sw[0],q[7:1]};
        end
        else begin
            q<= {q[6:0],sw[0]};
        end
    end
end





endmodule

lab6/shift_reg/wave.vcd
$version Generated by VerilatedVcd $end
$timescale 1ps $end
 $scope module TOP $end
  $var wire 1 # clk $end
  $var wire 1 $ rst $end
  $var wire 5 % btn [4:0] $end
  $var wire 16 & sw [15:0] $end
  $var wire 1 ' ps2_clk $end
  $var wire 1 ( ps2_data $end
  $var wire 16 ) ledr [15:0] $end
  $var wire 1 * VGA_CLK $end
  $var wire 1 + VGA_HSYNC $end
  $var wire 1 , VGA_VSYNC $end
  $var wire 1 - VGA_BLANK_N $end
  $var wire 8 . VGA_R [7:0] $end
  $var wire 8 / VGA_G [7:0] $end
  $var wire 8 0 VGA_B [7:0] $end
  $var wire 8 1 seg0 [7:0] $end
  $var wire 8 2 seg1 [7:0] $end
  $var wire 8 3 seg2 [7:0] $end
  $var wire 8 4 seg3 [7:0] $end
  $var wire 8 5 seg4 [7:0] $end
  $var wire 8 6 seg5 [7:0] $end
  $var wire 8 7 seg6 [7:0] $end
  $var wire 8 8 seg7 [7:0] $end
  $scope module top $end
   $var wire 1 # clk $end
   $var wire 1 $ rst $end
   $var wire 5 % btn [4:0] $end
   $var wire 16 & sw [15:0] $end
   $var wire 1 ' ps2_clk $end
   $var wire 1 ( ps2_data $end
   $var wire 16 ) ledr [15:0] $end
   $var wire 1 * VGA_CLK $end
   $var wire 1 + VGA_HSYNC $end
   $var wire 1 , VGA_VSYNC $end
   $var wire 1 - VGA_BLANK_N $end
   $var wire 8 . VGA_R [7:0] $end
   $var wire 8 / VGA_G [7:0] $end
   $var wire 8 0 VGA_B [7:0] $end
   $var wire 8 1 seg0 [7:0] $end
   $var wire 8 2 seg1 [7:0] $end
   $var wire 8 3 seg2 [7:0] $end
   $var wire 8 4 seg3 [7:0] $end
   $var wire 8 5 seg4 [7:0] $end
   $var wire 8 6 seg5 [7:0] $end
   $var wire 8 7 seg6 [7:0] $end
   $var wire 8 8 seg7 [7:0] $end
   $var wire 8 9 q [7:0] $end
  $upscope $end
 $upscope $end
$enddefinitions $end


#0
0#
0$
b00001 %
b1000000000000001 &
0'
0(
b0000000000000001 )
0*
0+
0,
0-
b00000000 .
b00000000 /
b00000000 0
b00000000 1
b00000000 2
b00000000 3
b00000000 4
b00000000 5
b00000000 6
b00000000 7
b00000000 8
b00000001 9
#1
b0000000000000011 )
b00000011 9
#2
b0000000000000111 )
b00000111 9
#3
b0000000000001111 )
b00001111 9
#4
b0000000000011111 )
b00011111 9
#5
b1000000000000000 &
b0000000000111110 )
b00111110 9
#6
b1000000000000001 &
b0000000001111101 )
b01111101 9
#7
b0000000011111011 )
b11111011 9
#8
b0000000000000001 &
b0000000011111101 )
b11111101 9
#9
b0000000011111110 )
b11111110 9
#10
b0000000011111111 )
b11111111 9
#11
b0000000000000000 &
b0000000001111111 )
b01111111 9
#12
b0000000000000001 &
b0000000010111111 )
b10111111 9
#13
b0000000011011111 )
b11011111 9
#14
b0000000011101111 )
b11101111 9
#15
b0000000011110111 )
b11110111 9
